pyasdf/__init__.py
pyasdf/asdf_data_set.py
pyasdf/compat.py
pyasdf/exceptions.py
pyasdf/header.py
pyasdf/inventory_utils.py
pyasdf/query.py
pyasdf/utils.py
pyasdf/watermark.py
pyasdf/scripts/__init__.py
pyasdf/scripts/sac2asdf.py
pyasdf/tests/__init__.py
pyasdf/tests/__main__.py
pyasdf/tests/test_asdf_data_set.py
pyasdf/tests/test_inventory_utils.py
pyasdf/tests/test_query.py
pyasdf/tests/test_scripts.py
pyasdf/tests/test_utils.py
pyasdf/tests/data/II.ABKT.xml
pyasdf/tests/data/big_station.xml
pyasdf/tests/data/example_schematic_processing_chain.xml
pyasdf/tests/data/multi_station_epoch.xml
pyasdf/tests/data/small_sample_data_set/AE.113A..BHE.mseed
pyasdf/tests/data/small_sample_data_set/AE.113A..BHN.mseed
pyasdf/tests/data/small_sample_data_set/AE.113A..BHZ.mseed
pyasdf/tests/data/small_sample_data_set/AE.113A..BH_.xml
pyasdf/tests/data/small_sample_data_set/TA.POKR..BHE.mseed
pyasdf/tests/data/small_sample_data_set/TA.POKR..BHN.mseed
pyasdf/tests/data/small_sample_data_set/TA.POKR..BHZ.mseed
pyasdf/tests/data/small_sample_data_set/TA.POKR..BH_.xml
pyasdf/tests/data/small_sample_data_set/quake.xml
pyasdf-0.8.2.dist-info/licenses/LICENSE.txt
pyasdf-0.8.2.dist-info/METADATA
pyasdf-0.8.2.dist-info/WHEEL
pyasdf-0.8.2.dist-info/top_level.txt
pyasdf-0.8.2.dist-info/RECORD
