Metadata-Version: 2.4
Name: pyasdf
Version: 0.8.2
Summary: Python module for the Adaptable Seismic Data Format (ASDF).
Author-email: Lion Krischer <lion.krischer@gmail.com>
License: BSD-3-Clause
Classifier: Development Status :: 5 - Production/Stable
Classifier: Environment :: Console
Classifier: Intended Audience :: Science/Research
Classifier: Intended Audience :: Developers
Classifier: License :: OSI Approved :: BSD License
Classifier: Operating System :: OS Independent
Classifier: Programming Language :: Python
Classifier: Programming Language :: Python :: 3
Classifier: Topic :: Scientific/Engineering
Classifier: Topic :: Scientific/Engineering :: Physics
Requires-Python: >=3.7
License-File: LICENSE.txt
Requires-Dist: colorama
Requires-Dist: dill
Requires-Dist: h5py
Requires-Dist: numpy
Requires-Dist: obspy>=1.2.1
Requires-Dist: packaging
Requires-Dist: prov
Dynamic: license-file
